pyatsa/__init__.py
pyatsa/atsa_cli.py
pyatsa/pyatsa.py
pyatsa/pyatsa_configs.py
pyatsa/pyatsa_make_inputs.py
pyatsa/utils.py
pyatsa/tests/test_pyatsa.py
pyatsa-0.2.dist-info/LICENSE
pyatsa-0.2.dist-info/WHEEL
pyatsa-0.2.dist-info/METADATA
pyatsa-0.2.dist-info/RECORD
