Metadata-Version: 2.1
Name: pyatsa
Version: 0.2
Summary: The ATSA cloud masking method for Planetscope 4-band imagery
Home-page: https://github.com/agroimpacts/pyatsa
License: UNKNOWN
Author: Ryan Avery
Author-email: ravery@ucsb.edu
Requires-Python: >=3.5
Classifier: Intended Audience :: Science/Research
Classifier: License :: OSI Approved :: MIT License
Classifier: Programming Language :: Python :: 3
Requires-Dist: numpy>=1.8
Requires-Dist: scipy>=1.3.0
Requires-Dist: scikit-image>=0.15
Requires-Dist: statsmodels>=0.10.0
Requires-Dist: scikit-learn>=0.21.2
Requires-Dist: xarray>=0.12.3
Requires-Dist: dask>=2.1.0
Requires-Dist: rasterio>=1.0.7
Requires-Dist: porder>=0.3.7
